setup.py
pyanna/__init__.py
pyanna/crypto.py
pyanna/response.py
pyanna.egg-info/PKG-INFO
pyanna.egg-info/SOURCES.txt
pyanna.egg-info/dependency_links.txt
pyanna.egg-info/requires.txt
pyanna.egg-info/top_level.txt
pyanna/cipher/__init__.py
pyanna/cipher/des3.py