Metadata-Version: 1.1
Name: pyanna
Version: 0.1.0
Summary: Especificaciones Plataforma AnnA
Home-page: https://bitbucket.org/lucasecom/especificaciones_simono/src/master/
Author: Ecom Developers
Author-email: simono@ecom.com.ar
License: BSD
Keywords: 3des
Platform: UNKNOWN
Classifier: Development Status :: 1 - Planning
Classifier: License :: OSI Approved :: GNU Lesser General Public License v2 (LGPLv2)
Classifier: Programming Language :: Python
Classifier: Programming Language :: Python :: 3.6
Classifier: Topic :: Utilities
